sqre_labkubespawner/__init__.py
sqre_labkubespawner/auth-new.py
sqre_labkubespawner/auth.py
sqre_labkubespawner/jhubsingleuser-new.py
sqre_labkubespawner/jhubsingleuser.py
sqre_labkubespawner/log.py
sqre_labkubespawner/singleuser.py
sqre_labkubespawner/singleuser_hub.py
sqre_labkubespawner/utils.py
sqre_labkubespawner-0.0.8.data/scripts/jupyter-singlelabuser
sqre_labkubespawner-0.0.8.dist-info/DESCRIPTION.rst
sqre_labkubespawner-0.0.8.dist-info/METADATA
sqre_labkubespawner-0.0.8.dist-info/RECORD
sqre_labkubespawner-0.0.8.dist-info/WHEEL
sqre_labkubespawner-0.0.8.dist-info/metadata.json
sqre_labkubespawner-0.0.8.dist-info/top_level.txt
